{
  "events": [
    {
      "title": "Chess",
      "filter": "Events",
      "color": "#000",
      "singleDate": "2022-11-26T05:00:00.000Z",
      "allDay": true,
      "id": 1
    },
    {
      "title": "Test",
      "filter": "Holidays",
      "color": "rgb(0,0,0)",
      "singleDate": "2022-11-28T05:00:00.000Z",
      "allDay": true,
      "id": 9
    },
    {
      "title": "Test",
      "filter": "Birthdays",
      "color": "rgb(0,0,0)",
      "singleDate": "2022-11-27T05:00:00.000Z",
      "allDay": true,
      "id": 10
    },
    {
      "title": "TEst Again",
      "filter": "Birthdays",
      "color": "rgb(0,0,0)",
      "singleDate": "2022-11-27T05:00:00.000Z",
      "allDay": true,
      "id": 11
    },
    {
      "title": "TEstga",
      "filter": "Events",
      "color": "rgb(0,0,0)",
      "singleDate": "2022-11-28T05:00:00.000Z",
      "allDay": true,
      "id": 12
    },
    {
      "title": "fadsff",
      "filter": "Reminders",
      "color": "rgb(0,0,0)",
      "singleDate": "2022-11-28T05:00:00.000Z",
      "allDay": true,
      "id": 13
    },
    {
      "title": "fasdfsdf",
      "filter": "Events",
      "color": "rgb(0,0,0)",
      "singleDate": "2022-11-28T05:00:00.000Z",
      "allDay": true,
      "id": 14
    },
    {
      "title": "fasdfdsfadsf",
      "filter": "Reminders",
      "color": "rgb(0,0,0)",
      "singleDate": "2022-11-27T05:00:00.000Z",
      "allDay": true,
      "id": 15
    },
    {
      "title": "Bearhole 10k",
      "filter": "Runs",
      "color": "rgb(255,255,255)",
      "startTime": "2022-11-27T10:00:00.000Z",
      "endTime": "2022-11-27T12:00:00.000Z",
      "allDay": false,
      "id": 16
    },
    {
      "title": "Basement Work",
      "filter": "Plyo",
      "color": "rgb(255,255,255)",
      "startTime": "2022-11-27T17:00:00.000Z",
      "endTime": "2022-11-27T18:00:00.000Z",
      "allDay": false,
      "id": 18
    },
    {
      "title": "Porch Match",
      "filter": "Chess",
      "color": "rgb(255,255,255)",
      "singleDate": "2022-11-27T05:00:00.000Z",
      "allDay": true,
      "id": 20
    },
    {
      "title": "rAIL tRAIL",
      "filter": "rIDES",
      "color": "rgb(255,255,255)",
      "startTime": "2022-11-27T14:00:00.000Z",
      "endTime": "2022-11-27T16:00:00.000Z",
      "allDay": false,
      "id": 21
    },
    {
      "title": "Test",
      "filter": "Plyo",
      "color": "rgb(255,255,255)",
      "singleDate": "2022-11-29T05:00:00.000Z",
      "allDay": true,
      "id": 22
    },
    {
      "title": "Trst",
      "filter": "Events",
      "color": "rgb(0,0,0)",
      "singleDate": "2022-11-30T05:00:00.000Z",
      "allDay": true,
      "id": 23
    },
    {
      "title": "fasdfasdf",
      "filter": "Holidays",
      "color": "rgb(0,0,0)",
      "singleDate": "2023-04-02T04:00:00.000Z",
      "allDay": true,
      "id": 24
    },
    {
      "title": "fasdfasdf",
      "filter": "Plyo",
      "color": "rgb(255,255,255)",
      "singleDate": "2023-04-02T04:00:00.000Z",
      "allDay": true,
      "id": 25
    },
    {
      "title": "fasdfasdfdsf",
      "filter": "Runs",
      "color": "rgb(255,255,255)",
      "singleDate": "2023-04-02T04:00:00.000Z",
      "allDay": true,
      "id": 26
    },
    {
      "title": "ffffff",
      "filter": "Chess",
      "color": "rgb(255,255,255)",
      "singleDate": "2023-04-02T04:00:00.000Z",
      "allDay": true,
      "id": 27
    },
    {
      "title": "fasdfasdf",
      "filter": "Runs",
      "color": "rgb(255,255,255)",
      "singleDate": "2023-04-02T04:00:00.000Z",
      "allDay": true,
      "id": 28
    },
    {
      "title": "Testing Times",
      "filter": "Chess",
      "color": "rgb(255,255,255)",
      "startTime": "2022-11-29T17:00:00.000Z",
      "endTime": "2022-11-29T20:00:00.000Z",
      "allDay": false,
      "id": 30
    },
    {
      "title": "Test",
      "filter": "Plyo",
      "color": "rgb(255,255,255)",
      "singleDate": "2022-12-11T05:00:00.000Z",
      "allDay": true,
      "id": 31
    },
    {
      "title": "lkjl;jk",
      "filter": "Holidays",
      "color": "rgb(0,0,0)",
      "startTime": "2022-12-11T17:00:00.000Z",
      "endTime": "2022-12-11T20:00:00.000Z",
      "allDay": false,
      "id": 32
    },
    {
      "title": "lllll",
      "filter": "Runs",
      "color": "rgb(255,255,255)",
      "singleDate": "2022-12-11T05:00:00.000Z",
      "allDay": true,
      "id": 33
    },
    {
      "title": "yyyyy",
      "filter": "Events",
      "color": "rgb(0,0,0)",
      "startTime": "2022-12-11T15:00:00.000Z",
      "endTime": "2022-12-11T17:00:00.000Z",
      "allDay": false,
      "id": 35
    },
    {
      "title": "fasdfsdf",
      "filter": "Plyo",
      "color": "rgb(255,255,255)",
      "startTime": "2022-12-12T03:00:00.000Z",
      "endTime": "2022-12-12T05:00:00.000Z",
      "allDay": false,
      "id": 36
    },
    {
      "title": "fasdfsdf",
      "filter": "Plyo",
      "color": "rgb(255,255,255)",
      "singleDate": "2022-12-11T05:00:00.000Z",
      "allDay": true,
      "id": 37
    },
    {
      "title": "fasdfadsf",
      "filter": "rIDES",
      "color": "rgb(255,255,255)",
      "singleDate": "2022-12-11T05:00:00.000Z",
      "allDay": true,
      "id": 38
    },
    {
      "title": "Birthday 50th",
      "filter": "Birthdays",
      "color": "rgb(0,0,0)",
      "singleDate": "2022-12-11T05:00:00.000Z",
      "allDay": true,
      "id": 39
    },
    {
      "title": "fasdfasdf",
      "filter": "Chess",
      "color": "rgb(255,255,255)",
      "startTime": "2022-12-11T20:00:00.000Z",
      "endTime": "2022-12-11T22:00:00.000Z",
      "allDay": false,
      "id": 40
    },
    {
      "title": "qqqqqqqq",
      "filter": "Runs",
      "color": "rgb(255,255,255)",
      "singleDate": "2022-11-28T05:00:00.000Z",
      "allDay": true,
      "id": 41
    },
    {
      "title": "fasdfasdf",
      "filter": "Plyo",
      "color": "rgb(255,255,255)",
      "startTime": "2022-11-26T17:00:00.000Z",
      "endTime": "2022-11-26T18:00:00.000Z",
      "allDay": false,
      "id": 42
    },
    {
      "title": "fasdfasdf",
      "filter": "Plyo",
      "color": "rgb(255,255,255)",
      "singleDate": "2022-12-18T05:00:00.000Z",
      "allDay": true,
      "id": 43
    }
  ]
}